kedro/__init__.py
kedro/__main__.py
kedro/py.typed
kedro/utils.py
kedro/config/__init__.py
kedro/config/config.py
kedro/config/default_logger.py
kedro/config/logging.yml
kedro/config/templated_config.py
kedro/extras/__init__.py
kedro/extras/datasets/__init__.py
kedro/extras/datasets/api/__init__.py
kedro/extras/datasets/api/api_dataset.py
kedro/extras/datasets/biosequence/__init__.py
kedro/extras/datasets/biosequence/biosequence_dataset.py
kedro/extras/datasets/dask/__init__.py
kedro/extras/datasets/dask/parquet_dataset.py
kedro/extras/datasets/email/__init__.py
kedro/extras/datasets/email/message_dataset.py
kedro/extras/datasets/geopandas/__init__.py
kedro/extras/datasets/geopandas/geojson_dataset.py
kedro/extras/datasets/holoviews/__init__.py
kedro/extras/datasets/holoviews/holoviews_writer.py
kedro/extras/datasets/json/__init__.py
kedro/extras/datasets/json/json_dataset.py
kedro/extras/datasets/matplotlib/__init__.py
kedro/extras/datasets/matplotlib/matplotlib_writer.py
kedro/extras/datasets/networkx/__init__.py
kedro/extras/datasets/networkx/networkx_dataset.py
kedro/extras/datasets/pandas/__init__.py
kedro/extras/datasets/pandas/appendable_excel_dataset.py
kedro/extras/datasets/pandas/csv_dataset.py
kedro/extras/datasets/pandas/excel_dataset.py
kedro/extras/datasets/pandas/feather_dataset.py
kedro/extras/datasets/pandas/gbq_dataset.py
kedro/extras/datasets/pandas/generic_dataset.py
kedro/extras/datasets/pandas/hdf_dataset.py
kedro/extras/datasets/pandas/json_dataset.py
kedro/extras/datasets/pandas/parquet_dataset.py
kedro/extras/datasets/pandas/sql_dataset.py
kedro/extras/datasets/pickle/__init__.py
kedro/extras/datasets/pickle/pickle_dataset.py
kedro/extras/datasets/pillow/__init__.py
kedro/extras/datasets/pillow/image_dataset.py
kedro/extras/datasets/plotly/__init__.py
kedro/extras/datasets/plotly/json_dataset.py
kedro/extras/datasets/plotly/plotly_dataset.py
kedro/extras/datasets/spark/__init__.py
kedro/extras/datasets/spark/deltatable_dataset.py
xedro-0.17.6.dist-info/LICENSE.md
xedro-0.17.6.dist-info/METADATA
xedro-0.17.6.dist-info/WHEEL
xedro-0.17.6.dist-info/entry_points.txt
xedro-0.17.6.dist-info/top_level.txt
xedro-0.17.6.dist-info/RECORD
