Metadata-Version: 2.1
Name: xedro
Version: 0.17.6
Summary: Kedro helps you build production-ready data and analytics pipelines
Home-page: https://github.com/quantumblacklabs/kedro
Author: QuantumBlack Labs
License: Apache Software License (Apache 2.0)
Keywords: pipelines,machine learning,data pipelines,data science,data engineering
Platform: UNKNOWN
Classifier: Development Status :: 4 - Beta
Classifier: Programming Language :: Python :: 3.6
Classifier: Programming Language :: Python :: 3.7
Classifier: Programming Language :: Python :: 3.8
Requires-Python: >=3.6, <3.10
License-File: LICENSE.md
Requires-Dist: anyconfig (~=0.10.0)
Requires-Dist: cachetools (~=4.1)
Requires-Dist: click (<8.0)
Requires-Dist: cookiecutter (~=1.7.0)
Requires-Dist: dynaconf (<4.0.0,>=3.1.2)
Requires-Dist: fsspec (<2022.01,>=2021.04)
Requires-Dist: gitpython (~=3.0)
Requires-Dist: jmespath (<1.0,>=0.9.5)
Requires-Dist: jupyter-client (<7.0,>=5.1)
Requires-Dist: pip-tools (~=6.4)
Requires-Dist: pluggy (~=0.13.0)
Requires-Dist: python-json-logger (~=2.0)
Requires-Dist: PyYAML (<6.0,>=4.2)
Requires-Dist: rope (~=0.21.0)
Requires-Dist: setuptools (>=38.0)
Requires-Dist: toml (~=0.10)
Requires-Dist: toposort (~=1.5)
Provides-Extra: all
Requires-Dist: Pillow (~=8.0) ; extra == 'all'
Requires-Dist: PyYAML (<6.0,>=4.2) ; extra == 'all'
Requires-Dist: SQLAlchemy (~=1.2) ; extra == 'all'
Requires-Dist: biopython (~=1.73) ; extra == 'all'
Requires-Dist: delta-spark (~=1.0) ; extra == 'all'
Requires-Dist: docutils (==0.16) ; extra == 'all'
Requires-Dist: geopandas (<1.0,>=0.6.0) ; extra == 'all'
Requires-Dist: hdfs (<3.0,>=2.5.8) ; extra == 'all'
Requires-Dist: holoviews (~=1.13.0) ; extra == 'all'
Requires-Dist: ipykernel (<7.0,>=5.3) ; extra == 'all'
Requires-Dist: ipython (~=7.10) ; extra == 'all'
Requires-Dist: matplotlib (<4.0,>=3.0.3) ; extra == 'all'
Requires-Dist: memory-profiler (<1.0,>=0.50.0) ; extra == 'all'
Requires-Dist: nbconvert (<6.0,>=5.3.1) ; extra == 'all'
Requires-Dist: nbformat (~=4.4) ; extra == 'all'
Requires-Dist: nbsphinx (==0.8.1) ; extra == 'all'
Requires-Dist: nbstripout (~=0.4) ; extra == 'all'
Requires-Dist: networkx (~=2.4) ; extra == 'all'
Requires-Dist: openpyxl (<4.0,>=3.0.3) ; extra == 'all'
Requires-Dist: pandas-gbq (<1.0,>=0.12.0) ; extra == 'all'
Requires-Dist: pandas (>=0.24) ; extra == 'all'
Requires-Dist: plotly (<6.0,>=4.8.0) ; extra == 'all'
Requires-Dist: pyarrow (<7.0,>=1.0) ; extra == 'all'
Requires-Dist: pyproj (<3.0,>=2.2.0) ; extra == 'all'
Requires-Dist: pyspark (<4.0,>=2.2) ; extra == 'all'
Requires-Dist: recommonmark (==0.7.1) ; extra == 'all'
Requires-Dist: requests (~=2.20) ; extra == 'all'
Requires-Dist: s3fs (<0.5,>=0.3.0) ; extra == 'all'
Requires-Dist: sphinx-autodoc-typehints (==1.11.1) ; extra == 'all'
Requires-Dist: sphinx-copybutton (==0.3.1) ; extra == 'all'
Requires-Dist: sphinx-rtd-theme (==0.4.1) ; extra == 'all'
Requires-Dist: sphinx (~=3.4.3) ; extra == 'all'
Requires-Dist: tables (~=3.6) ; extra == 'all'
Requires-Dist: tensorflow (~=2.0) ; extra == 'all'
Requires-Dist: xlrd (~=1.0) ; extra == 'all'
Requires-Dist: xlsxwriter (~=1.0) ; extra == 'all'
Requires-Dist: dask[complete] (~=2.6) ; (python_version == "3.6") and extra == 'all'
Requires-Dist: dask (<2022.01,>=2021.10.0) ; (python_version > "3.6") and extra == 'all'
Provides-Extra: api
Requires-Dist: requests (~=2.20) ; extra == 'api'
Provides-Extra: api.apidataset
Requires-Dist: requests (~=2.20) ; extra == 'api.apidataset'
Provides-Extra: biosequence
Requires-Dist: biopython (~=1.73) ; extra == 'biosequence'
Provides-Extra: biosequence.biosequencedataset
Requires-Dist: biopython (~=1.73) ; extra == 'biosequence.biosequencedataset'
Provides-Extra: dask
Provides-Extra: dask.parquetdataset
Requires-Dist: dask[complete] (~=2.6) ; (python_version == "3.6") and extra == 'dask.parquetdataset'
Requires-Dist: dask (<2022.01,>=2021.10.0) ; (python_version > "3.6") and extra == 'dask.parquetdataset'
Requires-Dist: dask[complete] (~=2.6) ; (python_version == "3.6") and extra == 'dask'
Requires-Dist: dask (<2022.01,>=2021.10.0) ; (python_version > "3.6") and extra == 'dask'
Provides-Extra: docs
Requires-Dist: docutils (==0.16) ; extra == 'docs'
Requires-Dist: sphinx (~=3.4.3) ; extra == 'docs'
Requires-Dist: sphinx-rtd-theme (==0.4.1) ; extra == 'docs'
Requires-Dist: nbsphinx (==0.8.1) ; extra == 'docs'
Requires-Dist: nbstripout (~=0.4) ; extra == 'docs'
Requires-Dist: recommonmark (==0.7.1) ; extra == 'docs'
Requires-Dist: sphinx-autodoc-typehints (==1.11.1) ; extra == 'docs'
Requires-Dist: sphinx-copybutton (==0.3.1) ; extra == 'docs'
Requires-Dist: ipykernel (<7.0,>=5.3) ; extra == 'docs'
Provides-Extra: geopandas
Requires-Dist: geopandas (<1.0,>=0.6.0) ; extra == 'geopandas'
Requires-Dist: pyproj (<3.0,>=2.2.0) ; extra == 'geopandas'
Provides-Extra: geopandas.geojsondataset
Requires-Dist: geopandas (<1.0,>=0.6.0) ; extra == 'geopandas.geojsondataset'
Requires-Dist: pyproj (<3.0,>=2.2.0) ; extra == 'geopandas.geojsondataset'
Provides-Extra: holoviews
Requires-Dist: holoviews (~=1.13.0) ; extra == 'holoviews'
Provides-Extra: holoviews.holoviewswriter
Requires-Dist: holoviews (~=1.13.0) ; extra == 'holoviews.holoviewswriter'
Provides-Extra: ipython
Requires-Dist: ipython (~=7.10) ; extra == 'ipython'
Provides-Extra: matplotlib
Requires-Dist: matplotlib (<4.0,>=3.0.3) ; extra == 'matplotlib'
Provides-Extra: matplotlib.matplotlibwriter
Requires-Dist: matplotlib (<4.0,>=3.0.3) ; extra == 'matplotlib.matplotlibwriter'
Provides-Extra: networkx
Requires-Dist: networkx (~=2.4) ; extra == 'networkx'
Provides-Extra: networkx.networkxdataset
Requires-Dist: networkx (~=2.4) ; extra == 'networkx.networkxdataset'
Provides-Extra: notebook_templates
Requires-Dist: nbconvert (<6.0,>=5.3.1) ; extra == 'notebook_templates'
Requires-Dist: nbformat (~=4.4) ; extra == 'notebook_templates'
Provides-Extra: pandas
Requires-Dist: SQLAlchemy (~=1.2) ; extra == 'pandas'
Requires-Dist: openpyxl (<4.0,>=3.0.3) ; extra == 'pandas'
Requires-Dist: pandas-gbq (<1.0,>=0.12.0) ; extra == 'pandas'
Requires-Dist: pandas (>=0.24) ; extra == 'pandas'
Requires-Dist: pyarrow (<7.0,>=1.0) ; extra == 'pandas'
Requires-Dist: tables (~=3.6) ; extra == 'pandas'
Requires-Dist: xlrd (~=1.0) ; extra == 'pandas'
Requires-Dist: xlsxwriter (~=1.0) ; extra == 'pandas'
Provides-Extra: pandas.appendableexceldataset
Requires-Dist: pandas (>=0.24) ; extra == 'pandas.appendableexceldataset'
Requires-Dist: openpyxl (<4.0,>=3.0.3) ; extra == 'pandas.appendableexceldataset'
Provides-Extra: pandas.csvdataset
Requires-Dist: pandas (>=0.24) ; extra == 'pandas.csvdataset'
Provides-Extra: pandas.exceldataset
Requires-Dist: pandas (>=0.24) ; extra == 'pandas.exceldataset'
Requires-Dist: xlrd (~=1.0) ; extra == 'pandas.exceldataset'
Requires-Dist: xlsxwriter (~=1.0) ; extra == 'pandas.exceldataset'
Provides-Extra: pandas.featherdataset
Requires-Dist: pandas (>=0.24) ; extra == 'pandas.featherdataset'
Provides-Extra: pandas.gbqquerydataset
Requires-Dist: pandas (>=0.24) ; extra == 'pandas.gbqquerydataset'
Requires-Dist: pandas-gbq (<1.0,>=0.12.0) ; extra == 'pandas.gbqquerydataset'
Provides-Extra: pandas.gbqtabledataset
Requires-Dist: pandas (>=0.24) ; extra == 'pandas.gbqtabledataset'
Requires-Dist: pandas-gbq (<1.0,>=0.12.0) ; extra == 'pandas.gbqtabledataset'
Provides-Extra: pandas.genericdataset
Requires-Dist: pandas (>=0.24) ; extra == 'pandas.genericdataset'
Provides-Extra: pandas.hdfdataset
Requires-Dist: pandas (>=0.24) ; extra == 'pandas.hdfdataset'
Requires-Dist: tables (~=3.6) ; extra == 'pandas.hdfdataset'
Provides-Extra: pandas.jsondataset
Requires-Dist: pandas (>=0.24) ; extra == 'pandas.jsondataset'
Provides-Extra: pandas.parquetdataset
Requires-Dist: pandas (>=0.24) ; extra == 'pandas.parquetdataset'
Requires-Dist: pyarrow (<7.0,>=1.0) ; extra == 'pandas.parquetdataset'
Provides-Extra: pandas.sqlquerydataset
Requires-Dist: pandas (>=0.24) ; extra == 'pandas.sqlquerydataset'
Requires-Dist: SQLAlchemy (~=1.2) ; extra == 'pandas.sqlquerydataset'
Provides-Extra: pandas.sqltabledataset
Requires-Dist: pandas (>=0.24) ; extra == 'pandas.sqltabledataset'
Requires-Dist: SQLAlchemy (~=1.2) ; extra == 'pandas.sqltabledataset'
Provides-Extra: pillow
Requires-Dist: Pillow (~=8.0) ; extra == 'pillow'
Provides-Extra: pillow.imagedataset
Requires-Dist: Pillow (~=8.0) ; extra == 'pillow.imagedataset'
Provides-Extra: plotly
Requires-Dist: pandas (>=0.24) ; extra == 'plotly'
Requires-Dist: plotly (<6.0,>=4.8.0) ; extra == 'plotly'
Provides-Extra: plotly.jsondataset
Requires-Dist: plotly (<6.0,>=4.8.0) ; extra == 'plotly.jsondataset'
Provides-Extra: plotly.plotlydataset
Requires-Dist: pandas (>=0.24) ; extra == 'plotly.plotlydataset'
Requires-Dist: plotly (<6.0,>=4.8.0) ; extra == 'plotly.plotlydataset'
Provides-Extra: profilers
Requires-Dist: memory-profiler (<1.0,>=0.50.0) ; extra == 'profilers'
Provides-Extra: spark
Requires-Dist: delta-spark (~=1.0) ; extra == 'spark'
Requires-Dist: hdfs (<3.0,>=2.5.8) ; extra == 'spark'
Requires-Dist: pyspark (<4.0,>=2.2) ; extra == 'spark'
Requires-Dist: s3fs (<0.5,>=0.3.0) ; extra == 'spark'
Provides-Extra: spark.deltatabledataset
Requires-Dist: pyspark (<4.0,>=2.2) ; extra == 'spark.deltatabledataset'
Requires-Dist: hdfs (<3.0,>=2.5.8) ; extra == 'spark.deltatabledataset'
Requires-Dist: s3fs (<0.5,>=0.3.0) ; extra == 'spark.deltatabledataset'
Requires-Dist: delta-spark (~=1.0) ; extra == 'spark.deltatabledataset'
Provides-Extra: spark.sparkdataset
Requires-Dist: pyspark (<4.0,>=2.2) ; extra == 'spark.sparkdataset'
Requires-Dist: hdfs (<3.0,>=2.5.8) ; extra == 'spark.sparkdataset'
Requires-Dist: s3fs (<0.5,>=0.3.0) ; extra == 'spark.sparkdataset'
Provides-Extra: spark.sparkhivedataset
Requires-Dist: pyspark (<4.0,>=2.2) ; extra == 'spark.sparkhivedataset'
Requires-Dist: hdfs (<3.0,>=2.5.8) ; extra == 'spark.sparkhivedataset'
Requires-Dist: s3fs (<0.5,>=0.3.0) ; extra == 'spark.sparkhivedataset'
Provides-Extra: spark.sparkjdbcdataset
Requires-Dist: pyspark (<4.0,>=2.2) ; extra == 'spark.sparkjdbcdataset'
Requires-Dist: hdfs (<3.0,>=2.5.8) ; extra == 'spark.sparkjdbcdataset'
Requires-Dist: s3fs (<0.5,>=0.3.0) ; extra == 'spark.sparkjdbcdataset'
Provides-Extra: tensorflow
Requires-Dist: tensorflow (~=2.0) ; extra == 'tensorflow'
Provides-Extra: tensorflow.tensorflowmodeldataset
Requires-Dist: tensorflow (~=2.0) ; extra == 'tensorflow.tensorflowmodeldataset'
Provides-Extra: yaml
Requires-Dist: PyYAML (<6.0,>=4.2) ; extra == 'yaml'
Requires-Dist: pandas (>=0.24) ; extra == 'yaml'
Provides-Extra: yaml.yamldataset
Requires-Dist: pandas (>=0.24) ; extra == 'yaml.yamldataset'
Requires-Dist: PyYAML (<6.0,>=4.2) ; extra == 'yaml.yamldataset'
